aretomo/__init__.py
aretomo/aretomo_logo.png
aretomo/bibtex.py
aretomo/constants.py
aretomo/protocols.conf
aretomo/convert/__init__.py
aretomo/convert/convert.py
aretomo/convert/dataimport.py
aretomo/protocols/__init__.py
aretomo/protocols/protocol_aretomo.py
aretomo/tests/__init__.py
aretomo/tests/test_aretomo.py
scipion_em_aretomo-3.10.3.dist-info/LICENSE
scipion_em_aretomo-3.10.3.dist-info/METADATA
scipion_em_aretomo-3.10.3.dist-info/WHEEL
scipion_em_aretomo-3.10.3.dist-info/entry_points.txt
scipion_em_aretomo-3.10.3.dist-info/top_level.txt
scipion_em_aretomo-3.10.3.dist-info/RECORD
