Metadata-Version: 2.1
Name: scipion-em-aretomo
Version: 3.10.3
Summary: Plugin to use aretomo within the Scipion framework
Author-email: Scipion Team <scipion@cnb.csic.es>
License: GNU General Public License v3 (GPLv3)
Project-URL: Homepage, https://github.com/scipion-em/scipion-em-aretomo
Project-URL: Issues, https://github.com/scipion-em/scipion-em-aretomo/issues
Keywords: scipion,cryoem,cryoet,imageprocessing,scipion-3.0
Classifier: Development Status :: 4 - Beta
Classifier: License :: OSI Approved :: GNU General Public License v3 (GPLv3)
Classifier: Programming Language :: Python :: 3
Requires-Python: >=3.8
License-File: LICENSE
Requires-Dist: scipion-em>=3.5.0
Requires-Dist: scipion-em-tomo>=3.10.0
Requires-Dist: scipion-pyworkflow>=3.0.30
Requires-Dist: numpy>=1.23.0
